{
  "id": "craftable_mob_blueprint_ent",
  "nameTerm": "card_ent_name",
  "group": "Cooking",
  "subprints": [
  {
    "RequiredCards": "tree,magic_dust",
    "ResultCard": "ent",
    "Time": 10,
    "StatusTerm": "craftable_mob_idea_ent_status",
  },
  {
    "RequiredCards": "apple_tree,magic_dust",
    "ResultCard": "ent",
    "Time": 10,
    "StatusTerm": "craftable_mob_idea_ent_status"
  },
  {
    "RequiredCards": "banana_tree,magic_dust",
    "ResultCard": "ent",
    "Time": 10,
    "StatusTerm": "craftable_mob_idea_ent_status"
  },
  {
    "RequiredCards": "olive_tree,magic_dust",
    "ResultCard": "ent",
    "Time": 10,
    "StatusTerm": "craftable_mob_idea_ent_status"
  }
  ]
}
